brighteyes_ism/__init__.py
brighteyes_ism/analysis/APR_lib.py
brighteyes_ism/analysis/Deconv_lib.py
brighteyes_ism/analysis/FRC_lib.py
brighteyes_ism/analysis/FocusISM_lib.py
brighteyes_ism/analysis/Graph_lib.py
brighteyes_ism/analysis/Tools_lib.py
brighteyes_ism/analysis/__init__.py
brighteyes_ism/dataio/__init__.py
brighteyes_ism/dataio/mcs.py
brighteyes_ism/simulation/PSF_sim.py
brighteyes_ism/simulation/Tubulin_sim.py
brighteyes_ism/simulation/__init__.py
brighteyes_ism/simulation/detector.py
brighteyes_ism/simulation/simulator.py
brighteyes_ism/simulation/utils.py
brighteyes_ism-1.4.0.dist-info/licenses/LICENSE
brighteyes_ism-1.4.0.dist-info/METADATA
brighteyes_ism-1.4.0.dist-info/WHEEL
brighteyes_ism-1.4.0.dist-info/top_level.txt
brighteyes_ism-1.4.0.dist-info/RECORD
