Metadata-Version: 2.4
Name: brighteyes-ism
Version: 1.4.0
Summary: A toolbox for analysing and simulating ISM images
Home-page: https://github.com/VicidominiLab/brighteyes-ism
Author: Alessandro Zunino
Author-email: Alessandro Zunino <alessandro.zunino@iit.it>
Project-URL: Homepage, https://github.com/VicidominiLab/brighteyes-ism
Project-URL: Documentation, https://brighteyes-ism.readthedocs.io
Classifier: Programming Language :: Python :: 3.7
Classifier: Programming Language :: Python :: 3.8
Classifier: Programming Language :: Python :: 3.9
Classifier: Programming Language :: Python :: 3.10
Classifier: Operating System :: OS Independent
Classifier: License :: OSI Approved :: GNU General Public License v3 or later (GPLv3+)
Requires-Python: >=3.7
License-File: LICENSE
Requires-Dist: numpy
Requires-Dist: scipy
Requires-Dist: scikit-image
Requires-Dist: scikit-learn
Requires-Dist: matplotlib
Requires-Dist: joblib
Requires-Dist: tqdm
Requires-Dist: h5py
Requires-Dist: statsmodels
Requires-Dist: matplotlib-scalebar
Requires-Dist: torch
Requires-Dist: torchvision
Requires-Dist: zernikepy
Requires-Dist: psf-generator<=0.0.2
Provides-Extra: testing
Requires-Dist: tox; extra == "testing"
Requires-Dist: pytest; extra == "testing"
Requires-Dist: pytest-cov; extra == "testing"
Requires-Dist: pytest-qt; extra == "testing"
Requires-Dist: napari; extra == "testing"
Requires-Dist: pyqt5; extra == "testing"
Dynamic: license-file
